{
	"name": "SrcSnowflakeMobilityCoreDemo",
	"properties": {
		"linkedServiceName": {
			"referenceName": "Snowflake_UnityCloudFFA_MobilityCoreLocal",
			"type": "LinkedServiceReference"
		},
		"annotations": [],
		"type": "SnowflakeTable",
		"schema": [
			{
				"name": "SF_LOAD_TS",
				"type": "TIMESTAMP_NTZ",
				"precision": 29,
				"scale": 9
			},
			{
				"name": "TIMESTAMP",
				"type": "VARCHAR",
				"precision": 0,
				"scale": 0
			},
			{
				"name": "KUBERNETES_CONTAINER_NAME",
				"type": "VARCHAR",
				"precision": 0,
				"scale": 0
			},
			{
				"name": "KUBERNETES_HOST",
				"type": "VARCHAR",
				"precision": 0,
				"scale": 0
			},
			{
				"name": "KUBERNETES_CONTAINER_IMAGE",
				"type": "VARCHAR",
				"precision": 0,
				"scale": 0
			},
			{
				"name": "DOCKER_CONTAINER_ID",
				"type": "VARCHAR",
				"precision": 0,
				"scale": 0
			},
			{
				"name": "DEBUG_STRING",
				"type": "VARCHAR",
				"precision": 0,
				"scale": 0
			},
			{
				"name": "LOG",
				"type": "VARCHAR",
				"precision": 0,
				"scale": 0
			},
			{
				"name": "ORIGINAL_RECORD",
				"type": "VARIANT",
				"precision": 0,
				"scale": 0
			}
		],
		"typeProperties": {
			"schema": "MSLOGS",
			"table": "CSMF_FLUENTD_SMF_DEFAULT"
		}
	},
	"type": "Microsoft.DataFactory/factories/datasets"
}